Iris/Codec.py
Iris/Codec.pyi
Iris/__init__.py
Iris/__init__.pyi
Iris/iris_core.cpython-313-x86_64-linux-gnu.so
Iris/iris_core.pyi
Iris/Encoder/Encoder.pyi
Iris/Encoder/__init__.py
Iris/Encoder/__init__.pyi
Iris/Encoder/encoder.cpython-313-x86_64-linux-gnu.so
iris_codec-2025.3.1.dist-info/METADATA
iris_codec-2025.3.1.dist-info/WHEEL
iris_codec-2025.3.1.dist-info/RECORD
iris_codec-2025.3.1.dist-info/licenses/LICENSE
iris_codec-2025.3.1.dist-info/licenses/licenses/AVIF_LICENSE
iris_codec-2025.3.1.dist-info/licenses/licenses/HWY_LICENSE
iris_codec-2025.3.1.dist-info/licenses/licenses/JPEG_TURBO_LICENSE.md
iris_codec-2025.3.1.dist-info/licenses/licenses/LIBDICOM_LICENSE
iris_codec-2025.3.1.dist-info/licenses/licenses/PNG_LICENSE
iris_codec-2025.3.1.dist-info/licenses/licenses/ZLIB_LICENSE
