Metadata-Version: 2.1
Name: Iris-Codec
Version: 2025.3.1
Summary: Portable and blazingly fast whole slide image compression and serialization library for the Iris File Extension
Keywords: Iris,pathology,digital pathology,whole slide image,digital slide
Author-Email: Ryan Landvater <ryanlandvater@gmail.com>
Maintainer-Email: Ryan Landvater <ryanlandvater@gmail.com>
License: -----------------------------------------------------------------------------
Classifier: Development Status :: 4 - Beta
Classifier: Intended Audience :: Developers
Classifier: Topic :: Software Development :: Build Tools
Classifier: License :: OSI Approved :: MIT License
Classifier: Programming Language :: Python :: 3.11
Classifier: Programming Language :: Python :: 3.12
Classifier: Programming Language :: Python :: 3.13
Classifier: Programming Language :: Python :: 3 :: Only
Project-URL: Homepage, https://github.com/IrisDigitalPathology/Iris-Codec
Project-URL: Bug Reports, https://github.com/IrisDigitalPathology/Iris-Codec/issues
Project-URL: Source, https://github.com/IrisDigitalPathology/Iris-Codec
Requires-Python: >=3.11
Requires-Dist: openslide-bin
